rockblock_tools/__init__.py
rockblock_tools/command.py
rockblock_tools/exception.py
rockblock_tools/listen.py
rockblock_tools/send.py
rockblock_tools/formatter/__init__.py
rockblock_tools/formatter/console.py
rockblock_tools/formatter/csv.py
rockblock_tools/formatter/mqtt.py
rockblock_tools-0.0.4.dist-info/LICENSE
rockblock_tools-0.0.4.dist-info/METADATA
rockblock_tools-0.0.4.dist-info/WHEEL
rockblock_tools-0.0.4.dist-info/entry_points.txt
rockblock_tools-0.0.4.dist-info/top_level.txt
rockblock_tools-0.0.4.dist-info/RECORD
