Metadata-Version: 2.1
Name: rockblock-tools
Version: 0.0.4
Summary: RockBLOCK message sending and receiving tools
Home-page: https://github.com/oceotech/RockBLOCK-Python-Tools
Author: Andrew Carter
Author-email: andrewcarter1992@gmail.com
License: MIT
Keywords: rockblock 9603 iridium sbd tools
Platform: UNKNOWN
Classifier: Development Status :: 3 - Alpha
Classifier: Intended Audience :: Developers
Classifier: License :: OSI Approved :: MIT License
Classifier: Programming Language :: Python :: 2
Classifier: Programming Language :: Python :: 2.7
Classifier: Programming Language :: Python :: 3
Classifier: Programming Language :: Python :: 3.3
Classifier: Programming Language :: Python :: 3.4
Classifier: Programming Language :: Python :: 3.5
Classifier: Programming Language :: Python :: 3.6
Requires-Dist: flask
Requires-Dist: paho-mqtt
Requires-Dist: requests
Requires-Dist: six
